mapc_sim/__init__.py
mapc_sim/constants.py
mapc_sim/sim.py
mapc_sim/utils.py
mapc_sim/experimental/__init__.py
mapc_sim/experimental/graph.py
mapc_sim-0.2.1.dist-info/licenses/LICENSE
mapc_sim-0.2.1.dist-info/METADATA
mapc_sim-0.2.1.dist-info/WHEEL
mapc_sim-0.2.1.dist-info/top_level.txt
mapc_sim-0.2.1.dist-info/RECORD
