Metadata-Version: 2.4
Name: mapc_sim
Version: 0.2.1
Summary: IEEE 802.11 MAPC (C-SR) simulator
Author-email: Maksymilian Wojnar <maksymilian.wojnar@agh.edu.pl>, Wojciech Ciężobka <wojciech.ciezobka@agh.edu.pl>, Katarzyna Kosek-Szott <katarzyna.kosek-szott@agh.edu.pl>, Krzysztof Rusek <krzysztof.rusek@agh.edu.pl>, Szymon Szott <szymon.szott@agh.edu.pl>
License: Creative Commons Legal Code
Keywords: 802.11,coordinated spatial reuse,multi-access point coordination,simulator
Requires-Python: >=3.12
License-File: LICENSE
Requires-Dist: chex~=0.1.88
Requires-Dist: jax~=0.4.38
Requires-Dist: tensorflow-probability[jax]~=0.25.0
Provides-Extra: graph
Requires-Dist: jraph~=0.0.6.dev0; extra == "graph"
Dynamic: license-file
